pyCandle.cpython-310-x86_64-linux-gnu.so
candlesdk.libs/libblkid-a9167753.so.1.1.0
candlesdk.libs/libmount-ec61bd71.so.1.1.0
candlesdk.libs/libpcre2-8-516f4c9d.so.0.7.1
candlesdk.libs/libselinux-d0805dcb.so.1
candlesdk.libs/libudev-9765ffbd.so.1.6.11
candlesdk.libs/libusb-1-1b307d35.0.so.0.2.0
candlesdk.libs/libuuid-95b83d40.so.1.3.0
candlesdk-1.2.3.dist-info/METADATA
candlesdk-1.2.3.dist-info/WHEEL
candlesdk-1.2.3.dist-info/RECORD
candlesdk-1.2.3.dist-info/licenses/LICENSE.txt
