Metadata-Version: 2.2
Name: candlesdk
Version: 1.2.3
Summary: Python package for controlling MD-based actuators
Author-Email: MAB Robotics <support@mabrobotics.pl>
Maintainer-Email: MAB Robotics <support@mabrobotics.pl>
License: MIT License
Classifier: License :: OSI Approved :: GNU General Public License v3 (GPLv3)
Classifier: Natural Language :: English
Classifier: Programming Language :: Python :: 3.12
Classifier: Programming Language :: Python :: 3.13
Classifier: Programming Language :: C++
Classifier: Intended Audience :: Science/Research
Classifier: Programming Language :: Python :: Implementation :: CPython
Classifier: Operating System :: POSIX :: Linux
Requires-Python: >=3.10
Requires-Dist: cmake
